topsis102203633Danishsharma_core/__init__.py
topsis102203633Danishsharma_core/topsis.py
topsis102203633Danishsharma-1.0.1.dist-info/LICENSE
topsis102203633Danishsharma-1.0.1.dist-info/METADATA
topsis102203633Danishsharma-1.0.1.dist-info/WHEEL
topsis102203633Danishsharma-1.0.1.dist-info/top_level.txt
topsis102203633Danishsharma-1.0.1.dist-info/RECORD
