Metadata-Version: 2.1
Name: topsis102203633Danishsharma
Version: 1.0.1
Summary: A Python package for TOPSIS implementation
Author: Danish Sharma
Author-email: dsharma.workmain@gmail.com
Classifier: Programming Language :: Python :: 3.6
Classifier: License :: OSI Approved :: MIT License
Classifier: Operating System :: OS Independent
Requires-Python: >=3.6
License-File: LICENSE
Requires-Dist: numpy
Requires-Dist: pandas
Requires-Dist: scipy
Requires-Dist: matplotlib
Requires-Dist: SpeechRecognition
